keystone_role_assignment_openfga/__init__.py
keystone_role_assignment_openfga/config.py
keystone_role_assignment_openfga/multiplex_plugin.py
keystone_role_assignment_openfga/plugin.py
keystone_role_assignment_openfga/tests/test_plugin.py
keystone_role_assignment_openfga-0.1.0.dist-info/licenses/AUTHORS
keystone_role_assignment_openfga-0.1.0.dist-info/licenses/LICENSE
keystone_role_assignment_openfga-0.1.0.dist-info/METADATA
keystone_role_assignment_openfga-0.1.0.dist-info/WHEEL
keystone_role_assignment_openfga-0.1.0.dist-info/entry_points.txt
keystone_role_assignment_openfga-0.1.0.dist-info/pbr.json
keystone_role_assignment_openfga-0.1.0.dist-info/top_level.txt
keystone_role_assignment_openfga-0.1.0.dist-info/RECORD
